pkglic/__init__.py
pkglic/authinfo.py
pkglic/creditstemplate.txt
pkglic/pkglic.py
pkglic-1.0.9.dist-info/LICENSE
pkglic-1.0.9.dist-info/METADATA
pkglic-1.0.9.dist-info/WHEEL
pkglic-1.0.9.dist-info/entry_points.txt
pkglic-1.0.9.dist-info/top_level.txt
pkglic-1.0.9.dist-info/zip-safe
pkglic-1.0.9.dist-info/RECORD
