Metadata-Version: 2.1
Name: pkglic
Version: 1.0.9
Summary: Script to get the licenses of components used by js, py or c# apps.
Home-page: https://github.com/jhogstrom/pkglic
Author: Jesper Hogstrom
Author-email: jspr.hgstrm@gmail.com
License: MIT
Keywords: license,package,javascript,python,csharp
Platform: Operating System :: OS Independent
Classifier: Development Status :: 5 - Production/Stable
Classifier: Environment :: Console
Classifier: Intended Audience :: Developers
Classifier: License :: OSI Approved :: MIT License
Classifier: Operating System :: OS Independent
Classifier: Programming Language :: C#
Classifier: Programming Language :: Python
Classifier: Programming Language :: JavaScript
Classifier: Topic :: Software Development :: Documentation
Classifier: Topic :: Software Development :: Build Tools
Requires-Dist: requests
Requires-Dist: lxml
Requires-Dist: flake8
Requires-Dist: jinja2
